{
  "id": "Ivan_Petrov",
  "en": {
    "name": "Ivan Petrov",
    "yearsOfLife": "1935 - 1994",
    "location": "Minsk",
    "desc": "Great poet!",
    "timeline": [
      {
        "time": "1935",
        "description": "Born"
      }
    ],
    "poems": [
      {
        "group": "Poems",
        "works": [
          {
            "name": "Smoke on the water",
            "date": "1966"
          }
        ]
      }
    ],
    "video": "youtube",
    "mapId": "mapmapmap"
  },
  "ru": {
    "name": "Иван Петров",
    "yearsOfLife": "1935 - 1994",
    "location": "Minsk",
    "desc": "Великий поэт!",
    "timeline": [
      {
        "time": "1935",
        "description": "Родился"
      }
    ],
    "poems": [
      {
        "group": "Поэмы",
        "works": [
          {
            "name": "Дым над водой",
            "date": "1966"
          }
        ]
      }
    ],
    "video": "youtube",
    "mapId": "mapmapmap"
  },
  "be": {
    "name": "Иван Петроу",
    "yearsOfLife": "1935 - 1994",
    "location": "Минск",
    "desc": "Великий поэт",
    "timeline": [
      {
        "time": "1935",
        "description": "нарадзіўся"
      }
    ],
    "poems": [
      {
        "group": "поэмы",
        "works": [
          {
            "name": "дым над вадой",
            "date": "1966"
          }
        ]
      }
    ],
    "video": "youtube",
    "mapId": "mapmapmap"
  },
  "galleryImages": [
    {
      "image": "/assets/images/uploads/rickastley.jpg"
    }
  ]
}